lyra_graphtool_test/__init__.py
lyra_graphtool_test/configuration.py
lyra_graphtool_test/edge.py
lyra_graphtool_test/graph.py
lyra_graphtool_test/parameters.py
lyra_graphtool_test/utils.py
lyra_graphtool_test/vertex.py
lyra_graphtool_test/worker.py
lyra_graphtool_test-0.1.2.dist-info/LICENSE
lyra_graphtool_test-0.1.2.dist-info/METADATA
lyra_graphtool_test-0.1.2.dist-info/WHEEL
lyra_graphtool_test-0.1.2.dist-info/RECORD
