Metadata-Version: 2.1
Name: lyra-graphtool-test
Version: 0.1.2
Summary: Lyra Graphtool
License: Apache-2.0
Author: Studio X, LLC
Requires-Python: >=3.11,<4.0
Classifier: License :: OSI Approved :: Apache Software License
Classifier: Programming Language :: Python :: 3
Classifier: Programming Language :: Python :: 3.11
Requires-Dist: matplotlib (>=3.7.1,<4.0.0)
Requires-Dist: numpy (>=1.24.3,<2.0.0)
